betterproto/__init__.py
betterproto/casing.py
betterproto/plugin.py
betterproto/py.typed
betterproto/templates/template.py.j2
betterproto_for_temporal_python_sdk-1.2.5.dist-info/METADATA
betterproto_for_temporal_python_sdk-1.2.5.dist-info/WHEEL
betterproto_for_temporal_python_sdk-1.2.5.dist-info/entry_points.txt
betterproto_for_temporal_python_sdk-1.2.5.dist-info/top_level.txt
betterproto_for_temporal_python_sdk-1.2.5.dist-info/RECORD
