Metadata-Version: 2.1
Name: betterproto-for-temporal-python-sdk
Version: 1.2.5
Summary: A better Protobuf / gRPC generator & library
Home-page: https://github.com/firdaus/python-betterproto
Author: Mohammed Firdaus
Author-email: firdaus.halim@gmail.com
License: MIT
Platform: UNKNOWN
Requires-Python: >=3.6
Requires-Dist: grpclib
Requires-Dist: stringcase
Requires-Dist: dataclasses ; python_version < "3.7"
Requires-Dist: backports-datetime-fromisoformat ; python_version < "3.7"
Provides-Extra: compiler
Requires-Dist: black ; extra == 'compiler'
Requires-Dist: jinja2 ; extra == 'compiler'
Requires-Dist: protobuf ; extra == 'compiler'
